aus/__init__.py
aus/dependencies.py
aus/version.py
aus/dsl/__init__.py
aus/dsl/compiler/__init__.py
aus/dsl/compiler/compiler.py
aus/dsl/compiler/compiler_context.py
aus/dsl/compiler/compiler_utils.py
aus/dsl/compiler/constants.py
aus/dsl/compiler/node_inputs_compiler.py
aus/dsl/compiler/placeholder_utils.py
aus/dsl/context_managers/__init__.py
aus/dsl/context_managers/dsl_context.py
aus/dsl/context_managers/dsl_context_manager.py
aus/dsl/context_managers/dsl_context_registry.py
aus/dsl/control_flow/__init__.py
aus/dsl/control_flow/for_each.py
aus/dsl/control_flow/for_each_internal.py
aus/dsl/experimental/__init__.py
aus/dsl/experimental/conditionals/__init__.py
aus/dsl/experimental/conditionals/conditional.py
aus/dsl/experimental/node_execution_options/__init__.py
aus/dsl/experimental/node_execution_options/utils.py
aus/dsl/input_resolution/__init__.py
aus/dsl/input_resolution/resolver_function.py
aus/dsl/input_resolution/resolver_op.py
aus/dsl/input_resolution/ops/__init__.py
aus/dsl/input_resolution/ops/all_spans_op.py
aus/dsl/input_resolution/ops/consecutive_spans_op.py
aus/dsl/input_resolution/ops/exclude_spans_op.py
aus/dsl/input_resolution/ops/group_by_lineage_op.py
aus/dsl/input_resolution/ops/latest_create_time_op.py
aus/dsl/input_resolution/ops/latest_pipeline_run_outputs_op.py
aus/dsl/input_resolution/ops/latest_policy_model_op.py
aus/dsl/input_resolution/ops/latest_span_op.py
aus/dsl/input_resolution/ops/latest_version_op.py
aus/dsl/input_resolution/ops/ops.py
aus/dsl/input_resolution/ops/ops_utils.py
aus/dsl/input_resolution/ops/shuffle_op.py
aus/dsl/input_resolution/ops/skip_if_empty_op.py
aus/dsl/input_resolution/ops/skip_if_less_than_n_spans_op.py
aus/dsl/input_resolution/ops/sliding_window_op.py
aus/dsl/input_resolution/ops/static_span_range_op.py
aus/dsl/input_resolution/ops/unnest_op.py
aus/dsl/input_resolution/strategies/__init__.py
aus/dsl/input_resolution/strategies/conditional_strategy.py
aus-1.13.0.dev0.dist-info/METADATA
aus-1.13.0.dev0.dist-info/WHEEL
aus-1.13.0.dev0.dist-info/entry_points.txt
aus-1.13.0.dev0.dist-info/namespace_packages.txt
aus-1.13.0.dev0.dist-info/top_level.txt
aus-1.13.0.dev0.dist-info/RECORD
