Metadata-Version: 2.1
Name: aus
Version: 1.13.0.dev0
Summary: TensorFlow Extended (TFX) is a TensorFlow-based general-purpose machine learning platform implemented at Google.
Home-page: https://www.tensorflow.org/tfx
Download-URL: https://github.com/tensorflow/tfx/tags
Author: Google LLC
Author-email: tensorflow-extended-dev@googlegroups.com
License: Apache 2.0
Keywords: tensorflow tfx
Classifier: Development Status :: 5 - Production/Stable
Classifier: Intended Audience :: Developers
Classifier: Intended Audience :: Education
Classifier: Intended Audience :: Science/Research
Classifier: License :: OSI Approved :: Apache Software License
Classifier: Operating System :: OS Independent
Classifier: Programming Language :: Python
Classifier: Programming Language :: Python :: 3
Classifier: Programming Language :: Python :: 3.7
Classifier: Programming Language :: Python :: 3.8
Classifier: Programming Language :: Python :: 3.9
Classifier: Programming Language :: Python :: 3 :: Only
Classifier: Topic :: Scientific/Engineering
Classifier: Topic :: Scientific/Engineering :: Artificial Intelligence
Classifier: Topic :: Scientific/Engineering :: Mathematics
Classifier: Topic :: Software Development
Classifier: Topic :: Software Development :: Libraries
Classifier: Topic :: Software Development :: Libraries :: Python Modules
Requires-Python: >=3.7,<3.10
Requires-Dist: absl-py (<2.0.0,>=0.9)
Requires-Dist: ml-metadata (<1.13.0,>=1.12.0)
Requires-Dist: packaging (<21,>=20)
Requires-Dist: portpicker (<2,>=1.3.1)
Requires-Dist: protobuf (<4,>=3.13)
Requires-Dist: docker (<5,>=4.1)
Requires-Dist: google-apitools (<1,>=0.5)
Requires-Dist: google-api-python-client (<2,>=1.8)
Requires-Dist: jinja2 (<4,>=2.7.3)
Requires-Dist: typing-extensions (<5,>=3.10.0.2)
Requires-Dist: apache-beam[gcp] (<3,>=2.40)
Requires-Dist: attrs (<22,>=19.3.0)
Requires-Dist: click (<9,>=7)
Requires-Dist: numpy (<2,>=1.16)
Requires-Dist: pyarrow (<7,>=6)
Requires-Dist: pyyaml (<6,>=3.12)
Provides-Extra: all
Requires-Dist: apache-airflow[mysql] (<3,>=1.10.14) ; extra == 'all'
Requires-Dist: pytest (<7,>=5) ; extra == 'all'
Requires-Dist: struct2tensor (<0.44,>=0.43) ; extra == 'all'
Requires-Dist: websocket-client (<1,>=0.57) ; extra == 'all'
Provides-Extra: docker-image
Requires-Dist: mmh (<3,>=2.2) ; extra == 'docker-image'
Requires-Dist: python-snappy (<0.6,>=0.5) ; extra == 'docker-image'
Provides-Extra: test
Requires-Dist: apache-airflow[mysql] (<3,>=1.10.14) ; extra == 'test'
Requires-Dist: pytest (<7,>=5) ; extra == 'test'
